ts_chat/__init__.py
ts_chat/available_functions.py
ts_chat/chat2.py
ts_chat/execute_function.py
ts_chat/gemini2_test.py
ts_chat/gemini_test.py
ts_chat/main_api_caller.py
ts_chat/system_prompt.txt
tsbuddy/__init__.py
tsbuddy/__main__.py
tsbuddy/tsbuddy_menu.py
tsbuddy/aos/__init__.py
tsbuddy/aos/aosdl.py
tsbuddy/aos/aosdlv2.py
tsbuddy/aos/ga_index.json
tsbuddy/aos/ga_latest.json
tsbuddy/extracttar/__init__.py
tsbuddy/extracttar/extract_ts_tar.py
tsbuddy/extracttar/legacy/__init__.py
tsbuddy/extracttar/legacy/_extract_slow.py
tsbuddy/extracttar/legacy/extracttar_7zip.py
tsbuddy/hmon/__init__.py
tsbuddy/hmon/cpu_increase.py
tsbuddy/hmon/graph_cpu.py
tsbuddy/log_analyzer/__init__.py
tsbuddy/log_analyzer/get_techsupport.py
tsbuddy/log_analyzer/loganalyzer-reboots.py
tsbuddy/log_analyzer/logfinder.py
tsbuddy/log_analyzer/loglist-master.csv
tsbuddy/log_analyzer/logparser.py
tsbuddy/log_analyzer/logparser_v2.py
tsbuddy/tslog2csv/__init__.py
tsbuddy/tslog2csv/tslog2csv.py
tsbuddy/utils/__init__.py
tsbuddy/utils/clean_pycache.py
tsbuddy/utils/tsbuddy_version.py
tsbuddy-0.0.39.dist-info/METADATA
tsbuddy-0.0.39.dist-info/WHEEL
tsbuddy-0.0.39.dist-info/entry_points.txt
tsbuddy-0.0.39.dist-info/top_level.txt
tsbuddy-0.0.39.dist-info/RECORD
