Metadata-Version: 2.4
Name: tsbuddy
Version: 0.0.39
Summary: Tech Support Buddy is a versatile Python module built to empower developers and IT professionals in resolving technical issues. It provides a suite of Python functions designed to efficiently diagnose and resolve technical issues by parsing raw text into structured data, enabling automation and data-driven decision-making.
Requires-Dist: paramiko>=2.7.0
Requires-Dist: xlsxwriter>=3.2.5
Requires-Dist: scapy>=2.6.1
Requires-Dist: pandas>=2.3.1
Dynamic: description
Dynamic: description-content-type
Dynamic: requires-dist
Dynamic: summary
